easytensorboard/EasyTensorBoard.py
easytensorboard/__init__.py
EasyTensorBoard-1.0.0.dist-info/LICENSE
EasyTensorBoard-1.0.0.dist-info/METADATA
EasyTensorBoard-1.0.0.dist-info/WHEEL
EasyTensorBoard-1.0.0.dist-info/top_level.txt
EasyTensorBoard-1.0.0.dist-info/RECORD
