Metadata-Version: 2.1
Name: EasyTensorBoard
Version: 1.0.0
Summary: UNKNOWN
Home-page: UNKNOWN
Author: zhmh
Author-email: zhmhbest@gmail.com
License: MIT
Platform: UNKNOWN
Classifier: Programming Language :: Python :: 3
Classifier: License :: OSI Approved :: MIT License
Classifier: Operating System :: OS Independent
Requires-Python: >=3
Requires-Dist: tensorboard (>=1.8.0)
